konye_m_packages/__init__.py
konye_m_packages/preproc_functions.py
konye_m_packages-0.1.1.dist-info/METADATA
konye_m_packages-0.1.1.dist-info/WHEEL
konye_m_packages-0.1.1.dist-info/top_level.txt
konye_m_packages-0.1.1.dist-info/RECORD
